seeder/__init__.py
seeder/core.py
seeder/py.typed
seeder/service/__init__.py
seeder/service/minio_seeder.py
seeder/service/redis_seeder.py
seeder_py-0.1.3.dist-info/METADATA
seeder_py-0.1.3.dist-info/WHEEL
seeder_py-0.1.3.dist-info/licenses/LICENSE
seeder_py-0.1.3.dist-info/RECORD
